README.rst
setup.py
pymma/__init__.py
pymma/classes.py
pymma/cmd.py
pymma/constants.py
pymma/exceptions.py
pymma/functions.py
pymma.egg-info/PKG-INFO
pymma.egg-info/SOURCES.txt
pymma.egg-info/dependency_links.txt
pymma.egg-info/entry_points.txt
pymma.egg-info/not-zip-safe
pymma.egg-info/requires.txt
pymma.egg-info/top_level.txt