Metadata-Version: 1.0
Name: pymma
Version: 2.0.0
Summary: Python Multimon APRS
Home-page: http://github.com/ampledata/pymma
Author: Greg Albrecht
Author-email: oss@undef.net
License:                     GNU GENERAL PUBLIC LICENSE
